cse141Lproj/alu.sv
// combinational -- no clock
// sample -- change as desired
module alu(
  input[3:0] alu_cmd,     	// 16 ALU instructions
  
  // inA: rd (r4-r7), inB: rs (r0-r3)
  input[7:0] inA, 
  input[7:0] inB, 	 		// default inB value; unsigned
    
  output logic[7:0] rslt,
  // flag written to R1
  output logic out
);
  
  wire signed [7:0] inB_signed;  // signed version just for addi

  always_comb begin 
    rslt 	  = 'b0; 		// default result to 0
    out  	  = 'b0;    
    case(alu_cmd)
      // add: automatically makes carry-out
      'b0000: {out,rslt} = inA + inB;

      // sub: automatically makes carry-out
      'b0001: {out,rslt} = inA - inB;

      // bitwise not of 8-bit number
      'b0010: rslt = ~inB;	 // A = ~B

      // cmp: 1 if two values are equal, 0 if not
      'b0011: out = (inA == inB);

      // movl: move from r0–r3 to r4–r7
      'b0100: rslt = inB;
      
      // movr: move from r4–r7 to r0–r3
      'b0101: rslt = inA;
      
      // and: bitwise
      'b0110: rslt = inA & inB;
      
      // or: bitwise
      'b0111: rslt = inA | inB; 
      
      // addi: add immediate, automatically makes carry-out
      'b1000: {out,rslt} = inA + inB_signed;

      // sh: logical shift by imm; flags MSB / LBS of shift out
      'b1001: begin
        // imm is negative
        if (inB[7] == 'b1) begin
          out  = inA[7];
          // shift left by |imm|
          rslt    = inA << (~inB+1);   
        end 
        // imm is positive
        else begin			
          out  = inB[0];
          // shift right by |imm|
          rslt 	  = inA >> inB;		
        end 
      end 
      // nop: for ld, str, jump, beq
      default: rslt = 8'b0;
    endcase
  end
   
endmodule

cse141Lproj/alu_tb.sv
// used chatgpt to help with writing testbench
module alu_tb;
  // datB is 
  logic [7:0] a, b;
  logic [3:0] alu_cmd;
  logic [7:0] rslt;
  logic 	  flag_in;

  alu dut (
    .alu_cmd(alu_cmd),
    .inA(a),
    .inB(b),
    .rslt(rslt),
    .out(flag_in));

  initial begin
    $dumpfile("dump.vcd"); $dumpvars;
    // $dumpfile("alu.vcd");
    // $dumpvars(0, alu_tb);

    // Test ADD: alu_cmd = 0000
    a = 8'd18; b = 8'd49; alu_cmd = 'b0000; #10;
    $display("TEST: ADD, no c_out");
    $display("Expected: a=18 b=49 rslt=67 out=0 | Actual: a=%0d b=%0d rslt=%0d out=%0d", a, b, rslt, flag_in);
    $display();
    
    a = 8'd255; b = 8'd1; alu_cmd = 'b0000; #10;
    $display("TEST: ADD with c_out 1");
    $display("Expected: a=255 b=1 rslt=0 out=1 | Actual: a=%0d b=%0d rslt=%0d out=%0d", a, b, rslt, flag_in);
    $display();
    
    a = 8'd255; b = 8'd255; alu_cmd = 'b0000; #10;
    $display("TEST: ADD with c_out 2");
    $display("Expected: a=255 b=255 rslt=254 out=1 | Actual: a=%0d b=%0d rslt=%0d out=%0d", a, b, rslt, flag_in);
    $display();
    
    // Test SUB: alu_cmd = 0001
	
    // Test NOT: alu_cmd = 0010
    
    // Test CMP: alu_cmd = 0011
    a = 8'd27; b = 8'd27; alu_cmd = 'b0011; #10;
    $display("TEST: CMP equals");
    $display("Expected: a=27 b=27 rslt=0 out=1 | Actual: a=%0d b=%0d rslt=%0d out=%0d", a, b, rslt, flag_in);
    $display();
    
    // Test CMP: alu_cmd = 0011
    a = 8'd27; b = 8'd26; alu_cmd = 'b0011; #10;
    $display("TEST: CMP not equals");
    $display("Expected: a=27 b=26 rslt=0 out=0 | Actual: a=%0d b=%0d rslt=%0d out=%0d", a, b, rslt, flag_in);
    $display();
    
    // Test MOVL: alu_cmd = 0100
    a = 8'd27; b = 8'd26; alu_cmd = 'b0100; #10;
    $display("TEST: MOVL");
    $display("Expected: a=27 b=26 rslt=26 out=0 | Actual: a=%0d b=%0d rslt=%0d out=%0d", a, b, rslt, flag_in);
    $display();
    
    // Test MOVR: alu_cmd = 0101
    a = 8'd24; b = 8'd26; alu_cmd = 'b0101; #10;
    $display("TEST: MOVR");
    $display("Expected: a=24 b=26 rslt=24 out=0 | Actual: a=%0d b=%0d rslt=%0d out=%0d", a, b, rslt, flag_in);
    $display();
    
    // Test AND: alu_cmd = 0110
    a = 8'b0010_1111; b = 8'b1011_0010; alu_cmd = 'b0110; #10;
    $display("TEST: AND");
    $display("Expected: a=0010_1111 b=1011_0010 rslt=0010_0010 out=0 | Actual: a=%0b b=%0b rslt=%0b out=%0d", a, b, rslt, flag_in);
    $display();
    
    a = 8'b1011_1001; b = 8'b1111_1111; alu_cmd = 'b0110; #10;
    $display("TEST: AND: mask");
    $display("Expected: a=1011_1001 b=1111_1111 rslt=1011_1001 out=0 | Actual: a=%0b b=%0b rslt=%0b out=%0d", a, b, rslt, flag_in);
    $display();
    
    // Test OR: alu_cmd = 0111
    
    a = 8'b1011_1001; b = 8'b0; alu_cmd = 'b0110; #10;
    $display("TEST: AND: clear");
    $display("Expected: a=1011_1001 b=0 rslt=0 out=0 | Actual: a=%0b b=%0b rslt=%0b out=%0d", a, b, rslt, flag_in);
    $display();
    
    // Test: ADDI
    
    // Test: SH
    
    $finish;
  end
endmodule

cse141Lproj/dat_mem.sv
// 8-bit wide, 256-word (byte) deep memory array
module dat_mem (
  input[7:0] dat_in,
  input      clk,
  input      wr_en,	          // write enable
  input[7:0] addr,		      // address pointer
  output logic[7:0] dat_out);

  logic[7:0] core[256];       // 2-dim array  8 wide  256 deep

// reads are combinational; no enable or clock required
  assign dat_out = core[addr];

// writes are sequential (clocked) -- occur on stores or pushes 
  always_ff @(posedge clk) begin
    if(wr_en)				  // wr_en usually = 0; = 1 		
      core[addr] <= dat_in;
  end 

endmodule

cse141Lproj/reg_file.sv
// cache memory/register file
// we have 8 registers
module reg_file #(parameter pw=3)(
  input[7:0] dat_in,
  input      clk,
  input      wr_en,           // write enable
  input 	 flag, 		  	  // value of r1
  input		 flag_en,
  input[pw:0] 	wr_addr,	  // write address pointer
              	rd_addrA,	  // read address pointers
			  	rd_addrB,
  output logic[7:0] datA_out, // read data
                    datB_out);

  logic[7:0] core[2**pw];    // 2-dim array  8 wide 8 deep

// reads are combinational
// if reading from r0, always output 0
  assign datA_out = (rd_addrA == 0) ? 8'b0 : core[rd_addrA];
  assign datB_out = (rd_addrB == 0) ? 8'b0 : core[rd_addrB];


// writes are sequential (clocked)
  always_ff @(posedge clk) begin
  	// anything but stores or no ops
    
    // flag write to r1 has priority
    if (flag_en)
      core[1] <= {7'b0, flag}; 
    // prohibits you from writing to r0 / r1 
    else if(wr_en && wr_addr != 0 && wr_addr != 1)	
      core[wr_addr] <= dat_in; 
  end 

endmodule

cse141Lproj/Control.sv
// control decoder
// we use both funct and op; 15 instructions
// mcodebits is 4 bits to support <15 instructions
module Control #(parameter opwidth = 3, functwidth = 2, mcodebits = 4)(
  input [opwidth-1:0] 	 opcode,    
  input [functwidth-1:0] funct, 
  output logic RegDst, Branch, Jump,
     MemtoReg, MemWrite, ALUSrc, RegWrite, flag_en,
  output logic[mcodebits-1:0] ALUOp); // for 15 ALU operations

always_comb begin
// defaults
// We only use RegDst for move instructions. Default to rd
  RegDst 	=   'b0;    // 1: not in place  just leave 0
  Branch 	=   'b0;    // 1: conditional branch 
  Jump		= 	'b0;	// 1: uncondional jump
  MemWrite  =	'b0;    // 1: store to memory
  ALUSrc 	=	'b0;    // 1: immediate  0: second reg file output
  RegWrite  =	'b1;    // 0: for store or no op  1: most other operations 
  MemtoReg  =	'b0;    // 1: load -- route memory instead of ALU to reg_file data in 
  flag_en	=	'b0; 	// 1: update flag
  ALUOp	    =   'b1111; // nop? 

  // decode from opcode
  case(opcode)    
  // 000 or 001: r-type
  'b000:  begin	
    // signals same as default; only change ALUOp
    case(funct)
      // add
      'b00: begin
        ALUOp   = 'b0000;		// store carry out
        flag_en = 'b1;			
      // sub
      end 
      'b01: begin
        ALUOp   = 'b0001;		// store carry out
        flag_en = 'b1;			
      end 
      // not
      'b10: ALUOp = 'b0010;
      // cmp
      'b11: begin
        ALUOp   = 'b0011;
        flag_en = 'b1;
      end 
    endcase 
  end 
  'b001:  begin
    case(funct)
      // movl: left operant is dest (write in place, same as default)
      'b00: ALUOp = 'b0100;
      // movr: right operant is dest
      'b01: begin
        RegDst 	  = 'b1;
        ALUOp     = 'b0101;
      end 
      // and
      'b10: ALUOp = 'b0110;
      // or
      'b11: ALUOp = 'b0111;
    endcase 
  end 
  // i-type: ALUSrc = 1; imm is second operand  
  // 010: ld from mem
  'b010:  begin
    ALUSrc    	  = 'b1;   
    MemtoReg 	  = 'b1;	// load data from memory to reg
  end 
  // 011: str to mem
  'b011: begin 
    ALUSrc 		  = 'b1;	
    MemWrite 	  = 'b1;	// write to memory
    RegWrite	  = 'b0;	// 0 for store
  end 
  // 100: addi
  'b100: begin
    ALUSrc 		  = 'b1;
    flag_en		  = 'b1; 		// store carry out
    ALUOp 		  = 'b1000;

  end
  // 101: shift by imm
  'b101: begin
    ALUSrc 		  = 'b1;		
    flag_en		  = 'b1; 		// store shift out
    ALUOp 		  = 'b1001;
  end 
    
  // j-type
  // 110: jump
  'b110: begin
    Jump 		  = 'b1;		// enable Jump
    RegWrite 	  = 'b0; 		// don't write to register
  end 
  // 111: beq 
  'b111:  begin	
    Branch 		  = 'b1;		// enable Branch
    RegWrite 	  = 'b0; 		// don't write to register
  end 
  default: begin
	ALUOp		  = 'b1111;		// no op: loads & stores, branches
  end
endcase

end
	
endmodule

cse141Lproj/instr_ROM.sv
// lookup table
// deep 
// 9 bits wide; as deep as you wish
module instr_ROM #(parameter D=12)(
  input       [D-1:0] prog_ctr,    // prog_ctr	  address pointer
  output logic[ 8:0] mach_code);

  logic[8:0] core[2**D];
  initial							    // load the program
    $readmemb("mach_code.txt",core);

  always_comb  mach_code = core[prog_ctr];

endmodule

cse141Lproj/PC.sv
// program counter
// our ISA only supports both relative jumps
module PC #(parameter D=12)(
  input reset,					// synchronous reset
        clk,
  		req,
		reljump_en,             // rel. jump enable
  input       [D-1:0] offset,	// how far/where to jump
  output logic[D-1:0] prog_ctr
);

  always_ff @(posedge clk) begin
    if(reset)
	  prog_ctr <= '0;
    else if (req) begin
      if (reljump_en && (offset != 'b0))
        // target = prog_ctr + offset
        prog_ctr <= prog_ctr + offset;
        // no absolute addressing
  	  else
	  	prog_ctr <= prog_ctr + 1;
    end 
  end 

endmodule

cse141Lproj/top_level.sv
// sample top level design
module top_level(
  input        clk, reset, req, 
  output logic done);
  parameter D = 12,             // program counter width
    A = 4;             		    // ALU command bit width
  wire[D-1:0] prog_ctr; 			
              
  // flags for R1 (catch-all flag register)
  // carryout, shift out, cmp out
  logic  	  flag_in, 
  		      flag_out;				
  
  wire        RegDst,			// write in place or not
  			  Branch,			// conditional Branch enable
  			  Jump,				// unconditional Jump enable
   			  MemtoReg,
         	  MemWrite,
          	  ALUSrc,			// immediate switch
    		  flag_en,	  		// enable for R1
  			  RegWrite;	
  
  wire[A-1:0] alu_cmd;			// 4 bits; 16 ALU commands
  
  // instruction breakdown 
  wire [8:0]    mach_code;      // machine code
  wire [2:0]    opcode;
  wire [1:0]    rd_2bit;		// src1 and dest reg
  wire [1:0]    rs_2bit;		// src2 reg, only for r-type
  wire [1:0]    funct; 
  wire signed [7:0]    immed;	// 4-bit immediate, sign_ext to 8 bits
  wire [D-1:0]  offset;         // 6-bit offset, sign_ext to 12 bits
 
  // datA: rd (r4-r7), datB: rs (r0-r3)
  wire[7:0]   datA, datB,		// from RegFile
  			  mux1,				// write back to rd (def) or rs
  			  mux3,				// output of memory or reg
			  rslt;             // alu output
  
  wire signed [7:0] mux2;		// imm or reg output to alu
  
  // address pointers to reg_file; map from rs_2bit and rt_2bit
  wire[2:0] rd_addrA, rd_adrB;  
  
  // wires for output of memory and write back to reg
  wire [7:0] mem_out;
  
  // jump if either instruction is unconditional jump or we meet conditions for Branch
  assign PCSrc = Jump || (Branch && flag_out);

// fetch subassembly
  PC #(.D(D)) 					  // D: PC width
  pc1 (
    // inputs 
    .reset(reset), 
    .clk(clk), 
    .req(req),
    .reljump_en(PCSrc),  // remove the absolute jump enable
    .offset(offset), 
  	 // outputs
    .prog_ctr(prog_ctr));   

  // contains machine code
  instr_ROM ir1(
    // input 
    .prog_ctr(prog_ctr),
    // output
    .mach_code(mach_code));
    
  // decode machine code
  assign opcode  = mach_code[8:6];  // 3 bits opcode
  assign rd_2bit = mach_code[5:4];  // 2 bits rd (r4–r7 → addr 4–7)
  assign rs_2bit = mach_code[3:2];  // 2 bits rs (r0–r3 → addr 0–3)
  assign funct   = mach_code[1:0];  // 2 bits funct (r-type)
  
  // 4 bits immediate, sign extend to 8 bits (i-type)
  assign immed   = {{4{mach_code[3]}},mach_code[3:0]}; 
  // 6 bits offset, sign extend to 12 bits (j-type)
  assign offset  = {{6{mach_code[5]}},mach_code[5:0]};

  // map the registers
  assign rd_addrA = {1'b1, rd_2bit};    // rd (4–7)
  assign rd_addrB = {1'b0, rs_2bit};    // rs (0–3)
  
  // mux that decides write in place if RegDst = 0, don't if = 1
  assign mux1 = RegDst ? rd_addrB: rd_addrA; 
  
  // control decoder
  Control ctl1(
    // inputs
    .opcode(opcode), 
    .funct(funct),
    // outputs
    .RegDst(RegDst), 
    .Branch(Branch),  		// conditional Branch
    .Jump(Jump),			// unconditional Jump
    .MemtoReg(MemtoReg), 
    .MemWrite(MemWrite),  
    .ALUSrc(ALUSrc),  
    .ALUOp(alu_cmd),
    .flag_en(flag_en),		// enable flag update based on operation
    .RegWrite(RegWrite)      
  );
  
  /* for movr, addrA is dest reg. For all other 
	instructions, addrB is dest reg*/
  // register file
  reg_file #(.pw(3)) rf1(
    // inputs
    .clk(clk),
    .wr_en(RegWrite), 
    .flag_en(flag_en),		// wired from Control
    .rd_addrA(rd_addrA), 
    .rd_addrB(rd_addrB), 
    .wr_addr (mux1), 
    .dat_in(mux3),	   		// loads, most ops
    .flag(flag_in),			// r1: flag register
    // outputs
    .datA_out(datA), 
    .datB_out(datB));  
  
  // mux2 decides immediate or register data for ALU input
  assign mux2 = ALUSrc? immed : datB;
  
  alu alu1(
    // inputs
    .alu_cmd(alu_cmd),	    // from output of Control
    .inA(datA), 
    .inB(mux2),
    // outputs
    .rslt(rslt),
    .out(flag_in));			// all flags get written to one wire
  
  // mux to  write reg output or memory output back to reg
  assign mux3 = MemtoReg ? mem_out : rslt;

  // Write data to memory if MemWrite is enabled
  dat_mem dm1(
    // inputs
    .dat_in(datA),  		// from reg_file
    .clk(clk),
	.wr_en(MemWrite), 		// stores
    .addr(immed),			// absolute memory address
    // output 
    .dat_out(mem_out));		

// registered flags from ALU
  always_ff @(posedge clk or posedge reset) begin
    if (reset) 
      flag_out <= 'b0;
    else begin
      if (flag_en)
      	/* flag_out should be the stored value of flag_in so we can 
        	use it in a later cycle*/
        flag_out <= flag_in;
    end
  end

  assign done = prog_ctr == 128;
 
endmodule

cse141Lproj/dump.vcd
$date
	Thu May  8 17:30:22 2025
$end
$version
	QuestaSim Version 2024.3_1
$end
$timescale
	1ns
$end

$scope module top_level $end
$var wire 1 ! ALUSrc $end
$var wire 1 " Branch $end
$var wire 1 # Jump $end
$var wire 1 $ MemWrite $end
$var wire 1 % MemtoReg $end
$var wire 1 & PCSrc $end
$var wire 1 ' RegDst $end
$var wire 1 ( RegWrite $end
$var wire 1 ) alu_cmd [3] $end
$var wire 1 * alu_cmd [2] $end
$var wire 1 + alu_cmd [1] $end
$var wire 1 , alu_cmd [0] $end
$var wire 1 - clk $end
$var wire 1 . datA [7] $end
$var wire 1 / datA [6] $end
$var wire 1 0 datA [5] $end
$var wire 1 1 datA [4] $end
$var wire 1 2 datA [3] $end
$var wire 1 3 datA [2] $end
$var wire 1 4 datA [1] $end
$var wire 1 5 datA [0] $end
$var wire 1 6 datB [7] $end
$var wire 1 7 datB [6] $end
$var wire 1 8 datB [5] $end
$var wire 1 9 datB [4] $end
$var wire 1 : datB [3] $end
$var wire 1 ; datB [2] $end
$var wire 1 < datB [1] $end
$var wire 1 = datB [0] $end
$var wire 1 > flag_en $end
$var wire 1 ? funct [1] $end
$var wire 1 @ funct [0] $end
$var wire 1 A immed [7] $end
$var wire 1 B immed [6] $end
$var wire 1 C immed [5] $end
$var wire 1 D immed [4] $end
$var wire 1 E immed [3] $end
$var wire 1 F immed [2] $end
$var wire 1 G immed [1] $end
$var wire 1 H immed [0] $end
$var wire 1 I mach_code [8] $end
$var wire 1 J mach_code [7] $end
$var wire 1 K mach_code [6] $end
$var wire 1 L mach_code [5] $end
$var wire 1 M mach_code [4] $end
$var wire 1 N mach_code [3] $end
$var wire 1 O mach_code [2] $end
$var wire 1 P mach_code [1] $end
$var wire 1 Q mach_code [0] $end
$var wire 1 R mem_out [7] $end
$var wire 1 S mem_out [6] $end
$var wire 1 T mem_out [5] $end
$var wire 1 U mem_out [4] $end
$var wire 1 V mem_out [3] $end
$var wire 1 W mem_out [2] $end
$var wire 1 X mem_out [1] $end
$var wire 1 Y mem_out [0] $end
$var wire 1 Z mux1 [7] $end
$var wire 1 [ mux1 [6] $end
$var wire 1 \ mux1 [5] $end
$var wire 1 ] mux1 [4] $end
$var wire 1 ^ mux1 [3] $end
$var wire 1 _ mux1 [2] $end
$var wire 1 ` mux1 [1] $end
$var wire 1 a mux1 [0] $end
$var wire 1 b mux2 [7] $end
$var wire 1 c mux2 [6] $end
$var wire 1 d mux2 [5] $end
$var wire 1 e mux2 [4] $end
$var wire 1 f mux2 [3] $end
$var wire 1 g mux2 [2] $end
$var wire 1 h mux2 [1] $end
$var wire 1 i mux2 [0] $end
$var wire 1 j mux3 [7] $end
$var wire 1 k mux3 [6] $end
$var wire 1 l mux3 [5] $end
$var wire 1 m mux3 [4] $end
$var wire 1 n mux3 [3] $end
$var wire 1 o mux3 [2] $end
$var wire 1 p mux3 [1] $end
$var wire 1 q mux3 [0] $end
$var wire 1 r offset [11] $end
$var wire 1 s offset [10] $end
$var wire 1 t offset [9] $end
$var wire 1 u offset [8] $end
$var wire 1 v offset [7] $end
$var wire 1 w offset [6] $end
$var wire 1 x offset [5] $end
$var wire 1 y offset [4] $end
$var wire 1 z offset [3] $end
$var wire 1 { offset [2] $end
$var wire 1 | offset [1] $end
$var wire 1 } offset [0] $end
$var wire 1 ~ opcode [2] $end
$var wire 1 !! opcode [1] $end
$var wire 1 "! opcode [0] $end
$var wire 1 #! prog_ctr [11] $end
$var wire 1 $! prog_ctr [10] $end
$var wire 1 %! prog_ctr [9] $end
$var wire 1 &! prog_ctr [8] $end
$var wire 1 '! prog_ctr [7] $end
$var wire 1 (! prog_ctr [6] $end
$var wire 1 )! prog_ctr [5] $end
$var wire 1 *! prog_ctr [4] $end
$var wire 1 +! prog_ctr [3] $end
$var wire 1 ,! prog_ctr [2] $end
$var wire 1 -! prog_ctr [1] $end
$var wire 1 .! prog_ctr [0] $end
$var wire 2 /! rd_2bit [1:0] $end
$var wire 1 0! rd_addrA [2] $end
$var wire 1 1! rd_addrA [1] $end
$var wire 1 2! rd_addrA [0] $end
$var wire 1 3! rd_addrB $end
$var wire 3 4! rd_adrB [2:0] $end
$var wire 1 5! req $end
$var wire 1 6! reset $end
$var wire 2 7! rs_2bit [1:0] $end
$var wire 1 8! rslt [7] $end
$var wire 1 9! rslt [6] $end
$var wire 1 :! rslt [5] $end
$var wire 1 ;! rslt [4] $end
$var wire 1 <! rslt [3] $end
$var wire 1 =! rslt [2] $end
$var wire 1 >! rslt [1] $end
$var wire 1 ?! rslt [0] $end
$var parameter 32 @! A $end
$var parameter 32 A! D $end
$var reg 1 B! done $end
$var reg 1 C! flag_in $end
$var reg 1 D! flag_out $end

$scope module alu1 $end
$var wire 1 ) alu_cmd [3] $end
$var wire 1 * alu_cmd [2] $end
$var wire 1 + alu_cmd [1] $end
$var wire 1 , alu_cmd [0] $end
$var wire 1 . inA [7] $end
$var wire 1 / inA [6] $end
$var wire 1 0 inA [5] $end
$var wire 1 1 inA [4] $end
$var wire 1 2 inA [3] $end
$var wire 1 3 inA [2] $end
$var wire 1 4 inA [1] $end
$var wire 1 5 inA [0] $end
$var wire 1 b inB [7] $end
$var wire 1 c inB [6] $end
$var wire 1 d inB [5] $end
$var wire 1 e inB [4] $end
$var wire 1 f inB [3] $end
$var wire 1 g inB [2] $end
$var wire 1 h inB [1] $end
$var wire 1 i inB [0] $end
$var wire 8 E! inB_signed [7:0] $end
$var reg 1 F! out $end
$var reg 8 G! rslt [7:0] $end
$upscope $end

$scope module ctl1 $end
$var wire 1 ? funct [1] $end
$var wire 1 @ funct [0] $end
$var wire 1 ~ opcode [2] $end
$var wire 1 !! opcode [1] $end
$var wire 1 "! opcode [0] $end
$var parameter 32 H! functwidth $end
$var parameter 32 I! mcodebits $end
$var parameter 32 J! opwidth $end
$var reg 4 K! ALUOp [3:0] $end
$var reg 1 L! ALUSrc $end
$var reg 1 M! Branch $end
$var reg 1 N! Jump $end
$var reg 1 O! MemWrite $end
$var reg 1 P! MemtoReg $end
$var reg 1 Q! RegDst $end
$var reg 1 R! RegWrite $end
$var reg 1 S! flag_en $end
$upscope $end

$scope module dm1 $end
$var wire 1 A addr [7] $end
$var wire 1 B addr [6] $end
$var wire 1 C addr [5] $end
$var wire 1 D addr [4] $end
$var wire 1 E addr [3] $end
$var wire 1 F addr [2] $end
$var wire 1 G addr [1] $end
$var wire 1 H addr [0] $end
$var wire 1 - clk $end
$var wire 1 . dat_in [7] $end
$var wire 1 / dat_in [6] $end
$var wire 1 0 dat_in [5] $end
$var wire 1 1 dat_in [4] $end
$var wire 1 2 dat_in [3] $end
$var wire 1 3 dat_in [2] $end
$var wire 1 4 dat_in [1] $end
$var wire 1 5 dat_in [0] $end
$var wire 1 $ wr_en $end
$var reg 8 T! dat_out [7:0] $end
$upscope $end

$scope module ir1 $end
$var wire 1 #! prog_ctr [11] $end
$var wire 1 $! prog_ctr [10] $end
$var wire 1 %! prog_ctr [9] $end
$var wire 1 &! prog_ctr [8] $end
$var wire 1 '! prog_ctr [7] $end
$var wire 1 (! prog_ctr [6] $end
$var wire 1 )! prog_ctr [5] $end
$var wire 1 *! prog_ctr [4] $end
$var wire 1 +! prog_ctr [3] $end
$var wire 1 ,! prog_ctr [2] $end
$var wire 1 -! prog_ctr [1] $end
$var wire 1 .! prog_ctr [0] $end
$var parameter 32 U! D $end
$var reg 9 V! mach_code [8:0] $end
$upscope $end

$scope module pc1 $end
$var wire 1 - clk $end
$var wire 1 r offset [11] $end
$var wire 1 s offset [10] $end
$var wire 1 t offset [9] $end
$var wire 1 u offset [8] $end
$var wire 1 v offset [7] $end
$var wire 1 w offset [6] $end
$var wire 1 x offset [5] $end
$var wire 1 y offset [4] $end
$var wire 1 z offset [3] $end
$var wire 1 { offset [2] $end
$var wire 1 | offset [1] $end
$var wire 1 } offset [0] $end
$var wire 1 & reljump_en $end
$var wire 1 5! req $end
$var wire 1 6! reset $end
$var parameter 32 W! D $end
$var reg 12 X! prog_ctr [11:0] $end
$upscope $end

$scope module rf1 $end
$var wire 1 - clk $end
$var wire 1 j dat_in [7] $end
$var wire 1 k dat_in [6] $end
$var wire 1 l dat_in [5] $end
$var wire 1 m dat_in [4] $end
$var wire 1 n dat_in [3] $end
$var wire 1 o dat_in [2] $end
$var wire 1 p dat_in [1] $end
$var wire 1 q dat_in [0] $end
$var wire 1 Y! flag $end
$var wire 1 > flag_en $end
$var wire 1 Z! rd_addrA [3] $end
$var wire 1 0! rd_addrA [2] $end
$var wire 1 1! rd_addrA [1] $end
$var wire 1 2! rd_addrA [0] $end
$var wire 1 [! rd_addrB [3] $end
$var wire 1 \! rd_addrB [2] $end
$var wire 1 ]! rd_addrB [1] $end
$var wire 1 3! rd_addrB [0] $end
$var wire 1 ^ wr_addr [3] $end
$var wire 1 _ wr_addr [2] $end
$var wire 1 ` wr_addr [1] $end
$var wire 1 a wr_addr [0] $end
$var wire 1 ( wr_en $end
$var parameter 32 ^! pw $end
$var reg 8 _! datA_out [7:0] $end
$var reg 8 `! datB_out [7:0] $end
$upscope $end
$upscope $end

$scope module alu_tb $end
$var reg 8 a! a [7:0] $end
$var reg 4 b! alu_cmd [3:0] $end
$var reg 8 c! b [7:0] $end
$var reg 1 d! flag_in $end
$var reg 8 e! rslt [7:0] $end

$scope module dut $end
$var wire 1 f! alu_cmd [3] $end
$var wire 1 g! alu_cmd [2] $end
$var wire 1 h! alu_cmd [1] $end
$var wire 1 i! alu_cmd [0] $end
$var wire 1 j! inA [7] $end
$var wire 1 k! inA [6] $end
$var wire 1 l! inA [5] $end
$var wire 1 m! inA [4] $end
$var wire 1 n! inA [3] $end
$var wire 1 o! inA [2] $end
$var wire 1 p! inA [1] $end
$var wire 1 q! inA [0] $end
$var wire 1 r! inB [7] $end
$var wire 1 s! inB [6] $end
$var wire 1 t! inB [5] $end
$var wire 1 u! inB [4] $end
$var wire 1 v! inB [3] $end
$var wire 1 w! inB [2] $end
$var wire 1 x! inB [1] $end
$var wire 1 y! inB [0] $end
$var wire 8 z! inB_signed [7:0] $end
$var reg 1 {! out $end
$var reg 8 |! rslt [7:0] $end
$upscope $end
$upscope $end

$scope begin std $end
$upscope $end
$enddefinitions $end
#0
$dumpvars
bz z!
x.!
x-!
x,!
x+!
x*!
x)!
x(!
x'!
x&!
x%!
x$!
x#!
0'
0"
0#
0%
0$
0!
0>
1(
1,
1+
1*
1)
xQ
xP
xO
xN
xM
xL
xK
xJ
xI
x"!
x!!
x~
bx /!
bx 7!
x@
x?
xH
xG
xF
xE
xD
xC
xB
xA
x}
x|
x{
xz
xy
xx
xw
xv
xu
xt
xs
xr
x5
x4
x3
x2
x1
x0
x/
x.
x=
x<
x;
x:
x9
x8
x7
x6
xa
x`
1_
0^
0]
0\
0[
0Z
0q
0p
0o
0n
0m
0l
0k
0j
0?!
0>!
0=!
0<!
0;!
0:!
09!
08!
xi
xh
xg
xf
xe
xd
xc
xb
x2!
x1!
10!
bz 4!
xY
xX
xW
xV
xU
xT
xS
xR
0&
x3!
bz E!
1y!
0x!
0w!
0v!
1u!
1t!
0s!
0r!
0q!
1p!
0o!
0n!
1m!
0l!
0k!
0j!
0i!
0h!
0g!
0f!
z-
z6!
z5!
0Y!
zZ!
z]!
z\!
z[!
b100 @!
b1100 A!
xB!
0C!
xD!
b10010 a!
b0 b!
b110001 c!
0d!
b1000011 e!
0F!
b0 G!
b10 H!
b100 I!
b11 J!
b1111 K!
0L!
0M!
0N!
0O!
0P!
0Q!
1R!
0S!
bx T!
b1100 U!
bx V!
b1100 W!
bx X!
b11 ^!
bx _!
bx `!
0{!
b1000011 |!
$end
#10
b11111111 a!
b1 c!
0u!
0t!
1q!
1o!
1n!
1l!
1k!
1j!
b0 |!
1{!
1d!
b0 e!
#20
b11111111 c!
1x!
1w!
1v!
1u!
1t!
1s!
1r!
1{!
b11111110 |!
b11111110 e!
#30
b11011 a!
b11011 c!
b11 b!
1i!
1h!
0w!
0t!
0s!
0r!
0o!
0l!
0k!
0j!
b0 |!
1{!
b0 e!
#40
b11010 c!
0y!
0{!
0d!
#50
b100 b!
0i!
0h!
1g!
b11010 |!
b11010 e!
#60
b11000 a!
b101 b!
1i!
0q!
0p!
b11000 |!
b11000 e!
#70
b101111 a!
b10110010 c!
b110 b!
0i!
1h!
0v!
1t!
1r!
1q!
1p!
1o!
0m!
1l!
b100010 |!
b100010 e!
#80
b10111001 a!
b11111111 c!
1y!
1w!
1v!
1s!
0p!
0o!
1m!
1j!
b10111001 |!
b10111001 e!
#90
b0 c!
0y!
0x!
0w!
0v!
0u!
0t!
0s!
0r!
b0 |!
b0 e!
